Metadata-Version: 2.1
Name: odoo14-addon-sale_stock_analytic
Version: 14.0.1.0.1.dev5
Summary: Copies the analytic account of the sale order and the analytic tags of the sale order line to the stock move
Home-page: https://github.com/OCA/account-analytic
Author: ACSONE SA/NV,Odoo Community Association (OCA)
Author-email: support@odoo-community.org
License: AGPL-3
Classifier: Programming Language :: Python
Classifier: Framework :: Odoo
Classifier: Framework :: Odoo :: 14.0
Classifier: License :: OSI Approved :: GNU Affero General Public License v3
Requires-Python: >=3.6
Requires-Dist: odoo14-addon-stock-analytic
Requires-Dist: odoo<14.1dev,>=14.0a
